chronobiology/__init__.py
chronobiology/chronobiology.py
chronobiology-0.0.5.dist-info/LICENSE
chronobiology-0.0.5.dist-info/METADATA
chronobiology-0.0.5.dist-info/WHEEL
chronobiology-0.0.5.dist-info/top_level.txt
chronobiology-0.0.5.dist-info/RECORD
