Metadata-Version: 2.1
Name: chronobiology
Version: 0.0.5
Summary: A python package to calculate and plot circadian cycles data.
Home-page: https://github.com/ruslands/Chronobiology
Author: Ruslan Konovalov
Author-email: konovalov.rus@sjtu.edu.cn
License: UNKNOWN
Download-URL: https://github.com/ruslands/Chronobiology/archive/v0.0.4.tar.gz
Keywords: chronobiology,actogram,periodogram,sleep,analysis
Platform: UNKNOWN
Classifier: Programming Language :: Python :: 3
Classifier: License :: OSI Approved :: MIT License
Classifier: Operating System :: OS Independent
Requires-Python: >=3.6
License-File: LICENSE
Requires-Dist: influxdb (>=5.3.1)
Requires-Dist: pandas (>=1.1.5)
Requires-Dist: numpy (>=1.8.0)
Requires-Dist: matplotlib (>=3.3.4)
Requires-Dist: scipy (>=1.5.4)
